Workbook

Sheet Purchase Invoice (24 Dec 2025)
A1: TAX INVOICE — SONU PHARMA (PATNA)
A2: E-11 MAHIMA PLACES, M ROAD PATNA-4 | GSTIN: 10BRQPK2981Q2Z4 | Phone: 9801920752
A4: Billed To: | B4: M/s. ANAND PHARMA | G4: Invoice No: | H4: 1000343
A5: Address: | B5: V.I.P ROAD, ALLALPATTI, DARBHANGA, BIHAR (GSTIN: 10AEY3656A1Z4) | G5: Invoice Date: | H5: 24-12-2025
A7: S.No | B7: Product Name | C7: MFG / Pack | D7: Batch No | E7: Exp. Date | F7: MRP (₹) | G7: Purchase Rate (₹) | H7: Qty | I7: Total Amount (₹)
A8: 1 | B8: ALBEMETH PLUS INJ | C8: ALBER:2ML | D8: D25AM252 | E8: 03/2026 | F8: 131.7 | G8: 14 | H8: 20 | I8: =G8*H8
A9: 2 | B9: GLONIS AD 170 ML | C9: GLORI:1 | D9: AE-2547 | E9: 09/2027 | F9: 225 | G9: 60 | H9: 12 | I9: =G9*H9
A10: 3 | B10: ITRALBERT 200MG CAP | C10: ALBER:10*10 | D10: DE25019 | E10: 05/2026 | F10: 247.74 | G10: 68 | H10: 20 | I10: =G10*H10
A11: 4 | B11: KTSPERM 15GM | C11: LABOR:1*30 | D11: NKR-2536 | E11: 11/2027 | F11: 105 | G11: 13.75 | H11: 60 | I11: =G11*H11
A12: 5 | B12: KETOMAC SHAMPOO | C12: TORQU:75 | D12: B259230 | E12: 08/2026 | F12: 220 | G12: 130 | H12: 6 | I12: =G12*H12
A13: 6 | B13: CLOBETA GM 10GM | C13: LABOR:10 | D13: NC-2574 | E13: 04/2027 | F13: 73.75 | G13: 8.5 | H13: 144 | I13: =G13*H13
A14: 7 | B14: CALZAC CT CAP | C14: RANBA:200 | D14: GPA25034 | E14: 07/2026 | F14: 3450 | G14: 240 | H14: 3 | I14: =G14*H14
A15: 8 | B15: GENSOLIN TAB (20*10) | C15: MEDLE:200 | D15: VD25030 | E15: 02/2027 | F15: 3280 | G15: 240 | H15: 3 | I15: =G15*H15
A16: 9 | B16: MULTITEC CAP | C16: PEELI:20*10 | D16: ALD-2585 | E16: 10/2026 | F16: 3600 | G16: 190 | H16: 5 | I16: =G16*H16
A17: 10 | B17: RAJET LSR CAP | C17: NUEL:20*10 | D17: WHC2519 | E17: 08/2026 | F17: 198 | G17: 20 | H17: 100 | I17: =G17*H17
A18: 11 | B18: CALBERT K27 CAP | C18: ALBER:10*10 | D18: VHD2506 | E18: 05/2027 | F18: 2695 | G18: 325 | H18: 3 | I18: =G18*H18
A19: 12 | B19: PREGOUT-K1T | C19: MANKI:10*5 | D19: AAA2581 | E19: 11/2026 | F19: 4831 | G19: 410 | H19: 3 | I19: =G19*H19
... A51: 44 | B51: PROTISUN POWDER CHOCOLATE | C51: SUNLI:200GM | D51: AP-25313 | E51: 11/2026 | F51: 405 | G51: 36 | H51: 50 | I51: =G51*H51
H52: Sub Total | I52: =SUM(I8:I51)
H53: CGST (6%) | I53: =I52*0.06
H54: SGST (6%) | I54: =I52*0.06
H55: GRAND TOTAL | I55: =SUM(I52:I54)

Sheet Jan 2026
A1: Anand Pharma, Darbhanga — Inventory & Sales Register (Jan 2026)
A3: S.No | B3: Medicine Name | C3: Category | D3: MRP (₹) | E3: Purchase Price (₹) | F3: Opening Stock | G3: Purchase Qty | H3: Sales Qty | I3: Closing Stock | J3: Total Sales Revenue (₹) | K3: Expiry Date
A4: 1 | B4: Rabitec DSR Cap | C4: Gastric Care | D4: 185 | E4: 130 | F4: 49 | G4: 78 | H4: 52 | I4: 75 | J4: 9620 | K4: 08/2026
A5: 2 | B5: Montas L Tab (10s) | C5: Respiratory / Cold | D5: 165 | E5: 115 | F5: 70 | G5: 49 | H5: 73 | I5: 46 | J5: 12045 | K5: 05/2026
A6: 3 | B6: Calbert K27 Cap | C6: Calcium / Supplement | D6: 247 | E6: 175 | F6: 89 | G6: 33 | H6: 18 | I6: 104 | J6: 4446 | K6: 03/2026
A7: 4 | B7: Ceroxim CV 500 Tab | C7: Antibiotic | D7: 480 | E7: 340 | F7: 53 | G7: 78 | H7: 53 | I7: 78 | J7: 25440 | K7: 11/2026
A8: 5 | B8: Pantobert D Tab | C8: Gastric Care | D8: 140 | E8: 95 | F8: 87 | G8: 64 | H8: 33 | I8: 118 | J8: 4620 | K8: 09/2026
A9: 6 | B9: Moxabert CV 625 Tab | C9: Antibiotic | D9: 225 | E9: 160 | F9: 67 | G9: 48 | H9: 28 | I9: 87 | J9: 6300 | K9: 10/2026
A10: 7 | B10: Chyawanprash 2KG | C10: Ayurvedic / Immunity | D10: 450 | E10: 330 | F10: 57 | G10: 32 | H10: 28 | I10: 61 | J10: 12600 | K10: 12/2026
A11: 8 | B11: Dolo Pain Spray | C11: Pain Relief | D11: 195 | E11: 140 | F11: 36 | G11: 48 | H11: 25 | I11: 59 | J11: 4875 | K11: 04/2026
A12: 9 | B12: Abzolid 600 Tab | C12: Antibiotic | D12: 406 | E12: 285 | F12: 71 | G12: 32 | H12: 49 | I12: 54 | J12: 19894 | K12: 06/2026
A13: 10 | B13: Calbert D3 60K Cap | C13: Vitamin / Supplement | D13: 198 | E13: 135 | F13: 66 | G13: 35 | H13: 45 | I13: 56 | J13: 8910 | K13: 07/2026
A14: 11 | B14: Chymotas Forte Tab | C14: Pain / Swelling | D14: 370 | E14: 260 | F14: 76 | G14: 47 | H14: 55 | I14: 68 | J14: 20350 | K14: 05/2026
A15: 12 | B15: Skinshine Ointment 30g | C15: Dermatology | D15: 149 | E15: 105 | F15: 33 | G15: 47 | H15: 28 | I15: 52 | J15: 4172 | K15: 03/2026
... A33: 30 | B33: Moxib D Eye Drop | C33: Eye Care | D33: 110 | E33: 78 | F33: 69 | G33: 54 | H33: 17 | I33: 106 | J33: 1870 | K33: 06/2026

Sheet Feb 2026
A1: Anand Pharma, Darbhanga — Inventory & Sales Register (Feb 2026)
A3: S.No | B3: Medicine Name | C3: Category | D3: MRP (₹) | E3: Purchase Price (₹) | F3: Opening Stock | G3: Purchase Qty | H3: Sales Qty | I3: Closing Stock | J3: Total Sales Revenue (₹) | K3: Expiry Date
A4: 1 | B4: Rabitec DSR Cap | C4: Gastric Care | D4: 185 | E4: 130 | F4: 40 | G4: 63 | H4: 43 | I4: 60 | J4: 7955 | K4: 08/2026
A5: 2 | B5: Montas L Tab (10s) | C5: Respiratory / Cold | D5: 165 | E5: 115 | F5: 83 | G5: 70 | H5: 81 | I5: 72 | J5: 13365 | K5: 05/2026
A6: 3 | B6: Calbert K27 Cap | C6: Calcium / Supplement | D6: 247 | E6: 175 | F6: 42 | G6: 63 | H6: 55 | I6: 50 | J6: 13585 | K6: 03/2026
A7: 4 | B7: Ceroxim CV 500 Tab | C7: Antibiotic | D7: 480 | E7: 340 | F7: 50 | G7: 67 | H7: 26 | I7: 91 | J7: 12480 | K7: 11/2026
A8: 5 | B8: Pantobert D Tab | C8: Gastric Care | D8: 140 | E8: 95 | F8: 82 | G8: 76 | H8: 50 | I8: 108 | J8: 7000 | K8: 09/2026
A9: 6 | B9: Moxabert CV 625 Tab | C9: Antibiotic | D9: 225 | E9: 160 | F9: 35 | G9: 29 | H9: 23 | I9: 41 | J9: 5175 | K9: 10/2026
A10: 7 | B10: Chyawanprash 2KG | C10: Ayurvedic / Immunity | D10: 450 | E10: 330 | F10: 68 | G10: 44 | H10: 51 | I10: 61 | J10: 22950 | K10: 12/2026
A11: 8 | B11: Dolo Pain Spray | C11: Pain Relief | D11: 195 | E11: 140 | F11: 32 | G11: 55 | H11: 19 | I11: 68 | J11: 3705 | K11: 04/2026
A12: 9 | B12: Abzolid 600 Tab | C12: Antibiotic | D12: 406 | E12: 285 | F12: 69 | G12: 49 | H12: 50 | I12: 68 | J12: 20300 | K12: 06/2026
A13: 10 | B13: Calbert D3 60K Cap | C13: Vitamin / Supplement | D13: 198 | E13: 135 | F13: 49 | G13: 37 | H13: 18 | I13: 68 | J13: 3564 | K13: 07/2026
A14: 11 | B14: Chymotas Forte Tab | C14: Pain / Swelling | D14: 370 | E14: 260 | F14: 36 | G14: 37 | H14: 35 | I14: 38 | J14: 12950 | K14: 05/2026
A15: 12 | B15: Skinshine Ointment 30g | C15: Dermatology | D15: 149 | E15: 105 | F15: 57 | G15: 49 | H15: 24 | I15: 82 | J15: 3576 | K15: 03/2026
... A33: 30 | B33: Moxib D Eye Drop | C33: Eye Care | D33: 110 | E33: 78 | F33: 72 | G33: 21 | H33: 22 | I33: 71 | J33: 2420 | K33: 06/2026

Sheet Mar 2026
A1: Anand Pharma, Darbhanga — Inventory & Sales Register (Mar 2026)
A3: S.No | B3: Medicine Name | C3: Category | D3: MRP (₹) | E3: Purchase Price (₹) | F3: Opening Stock | G3: Purchase Qty | H3: Sales Qty | I3: Closing Stock | J3: Total Sales Revenue (₹) | K3: Expiry Date
A4: 1 | B4: Rabitec DSR Cap | C4: Gastric Care | D4: 185 | E4: 130 | F4: 50 | G4: 63 | H4: 43 | I4: 70 | J4: 7955 | K4: 08/2026
A5: 2 | B5: Montas L Tab (10s) | C5: Respiratory / Cold | D5: 165 | E5: 115 | F5: 90 | G5: 62 | H5: 38 | I5: 114 | J5: 6270 | K5: 05/2026
A6: 3 | B6: Calbert K27 Cap | C6: Calcium / Supplement | D6: 247 | E6: 175 | F6: 95 | G6: 33 | H6: 55 | I6: 73 | J6: 13585 | K6: 03/2026
A7: 4 | B7: Ceroxim CV 500 Tab | C7: Antibiotic | D7: 480 | E7: 340 | F7: 83 | G7: 54 | H7: 23 | I7: 114 | J7: 11040 | K7: 11/2026
A8: 5 | B8: Pantobert D Tab | C8: Gastric Care | D8: 140 | E8: 95 | F8: 65 | G8: 39 | H8: 50 | I8: 54 | J8: 7000 | K8: 09/2026
A9: 6 | B9: Moxabert CV 625 Tab | C9: Antibiotic | D9: 225 | E9: 160 | F9: 57 | G9: 35 | H9: 34 | I9: 58 | J9: 7650 | K9: 10/2026
A10: 7 | B10: Chyawanprash 2KG | C10: Ayurvedic / Immunity | D10: 450 | E10: 330 | F10: 51 | G10: 49 | H10: 42 | I10: 58 | J10: 18900 | K10: 12/2026
A11: 8 | B11: Dolo Pain Spray | C11: Pain Relief | D11: 195 | E11: 140 | F11: 30 | G11: 35 | H11: 34 | I11: 31 | J11: 6630 | K11: 04/2026
A12: 9 | B12: Abzolid 600 Tab | C12: Antibiotic | D12: 406 | E12: 285 | F12: 68 | G12: 67 | H12: 18 | I12: 117 | J12: 7308 | K12: 06/2026
A13: 10 | B13: Calbert D3 60K Cap | C13: Vitamin / Supplement | D13: 198 | E13: 135 | F13: 81 | G13: 62 | H13: 43 | I13: 100 | J13: 8514 | K13: 07/2026
A14: 11 | B14: Chymotas Forte Tab | C14: Pain / Swelling | D14: 370 | E14: 260 | F14: 59 | G14: 55 | H14: 18 | I14: 96 | J14: 6660 | K14: 05/2026
A15: 12 | B15: Skinshine Ointment 30g | C15: Dermatology | D15: 149 | E15: 105 | F15: 29 | G15: 69 | H15: 28 | I15: 70 | J15: 4172 | K15: 03/2026
... A33: 30 | B33: Moxib D Eye Drop | C33: Eye Care | D33: 110 | E33: 78 | F33: 41 | G33: 56 | H33: 47 | I33: 50 | J33: 5170 | K33: 06/2026

Sheet Apr 2026
A1: Anand Pharma, Darbhanga — Inventory & Sales Register (Apr 2026)
A3: S.No | B3: Medicine Name | C3: Category | D3: MRP (₹) | E3: Purchase Price (₹) | F3: Opening Stock | G3: Purchase Qty | H3: Sales Qty | I3: Closing Stock | J3: Total Sales Revenue (₹) | K3: Expiry Date
A4: 1 | B4: Rabitec DSR Cap | C4: Gastric Care | D4: 185 | E4: 130 | F4: 41 | G4: 27 | H4: 45 | I4: 23 | J4: 8325 | K4: 08/2026
A5: 2 | B5: Montas L Tab (10s) | C5: Respiratory / Cold | D5: 165 | E5: 115 | F5: 30 | G5: 48 | H5: 22 | I5: 56 | J5: 3630 | K5: 05/2026
A6: 3 | B6: Calbert K27 Cap | C6: Calcium / Supplement | D6: 247 | E6: 175 | F6: 36 | G6: 37 | H6: 54 | I6: 19 | J6: 13338 | K6: 03/2026
A7: 4 | B7: Ceroxim CV 500 Tab | C7: Antibiotic | D7: 480 | E7: 340 | F7: 42 | G7: 64 | H7: 40 | I7: 66 | J7: 19200 | K7: 11/2026
A8: 5 | B8: Pantobert D Tab | C8: Gastric Care | D8: 140 | E8: 95 | F8: 39 | G8: 38 | H8: 18 | I8: 59 | J8: 2520 | K8: 09/2026
A9: 6 | B9: Moxabert CV 625 Tab | C9: Antibiotic | D9: 225 | E9: 160 | F9: 32 | G9: 26 | H9: 48 | I9: 10 | J9: 10800 | K9: 10/2026
A10: 7 | B10: Chyawanprash 2KG | C10: Ayurvedic / Immunity | D10: 450 | E10: 330 | F10: 61 | G10: 35 | H10: 34 | I10: 62 | J10: 15300 | K10: 12/2026
A11: 8 | B11: Dolo Pain Spray | C11: Pain Relief | D11: 195 | E11: 140 | F11: 74 | G11: 61 | H11: 25 | I11: 110 | J11: 4875 | K11: 04/2026
A12: 9 | B12: Abzolid 600 Tab | C12: Antibiotic | D12: 406 | E12: 285 | F12: 73 | G12: 29 | H12: 50 | I12: 52 | J12: 20300 | K12: 06/2026
A13: 10 | B13: Calbert D3 60K Cap | C13: Vitamin / Supplement | D13: 198 | E13: 135 | F13: 67 | G13: 64 | H13: 55 | I13: 76 | J13: 10890 | K13: 07/2026
A14: 11 | B14: Chymotas Forte Tab | C14: Pain / Swelling | D14: 370 | E14: 260 | F14: 55 | G14: 39 | H14: 17 | I14: 77 | J14: 6290 | K14: 05/2026
A15: 12 | B15: Skinshine Ointment 30g | C15: Dermatology | D15: 149 | E15: 105 | F15: 55 | G15: 50 | H15: 39 | I15: 66 | J15: 5811 | K15: 03/2026
... A33: 30 | B33: Moxib D Eye Drop | C33: Eye Care | D33: 110 | E33: 78 | F33: 48 | G33: 46 | H33: 21 | I33: 73 | J33: 2310 | K33: 06/2026

Sheet May 2026
A1: Anand Pharma, Darbhanga — Inventory & Sales Register (May 2026)
A3: S.No | B3: Medicine Name | C3: Category | D3: MRP (₹) | E3: Purchase Price (₹) | F3: Opening Stock | G3: Purchase Qty | H3: Sales Qty | I3: Closing Stock | J3: Total Sales Revenue (₹) | K3: Expiry Date
A4: 1 | B4: Rabitec DSR Cap | C4: Gastric Care | D4: 185 | E4: 130 | F4: 59 | G4: 43 | H4: 60 | I4: 42 | J4: 11100 | K4: 08/2026
A5: 2 | B5: Montas L Tab (10s) | C5: Respiratory / Cold | D5: 165 | E5: 115 | F5: 61 | G5: 74 | H5: 28 | I5: 107 | J5: 4620 | K5: 05/2026
A6: 3 | B6: Calbert K27 Cap | C6: Calcium / Supplement | D6: 247 | E6: 175 | F6: 42 | G6: 68 | H6: 40 | I6: 70 | J6: 9880 | K6: 03/2026
A7: 4 | B7: Ceroxim CV 500 Tab | C7: Antibiotic | D7: 480 | E7: 340 | F7: 91 | G7: 62 | H7: 35 | I7: 118 | J7: 16800 | K7: 11/2026
A8: 5 | B8: Pantobert D Tab | C8: Gastric Care | D8: 140 | E8: 95 | F8: 63 | G8: 78 | H8: 64 | I8: 77 | J8: 8960 | K8: 09/2026
A9: 6 | B9: Moxabert CV 625 Tab | C9: Antibiotic | D9: 225 | E9: 160 | F9: 78 | G9: 76 | H9: 40 | I9: 114 | J9: 9000 | K9: 10/2026
A10: 7 | B10: Chyawanprash 2KG | C10: Ayurvedic / Immunity | D10: 450 | E10: 330 | F10: 30 | G10: 23 | H10: 48 | I10: 5 | J10: 21600 | K10: 12/2026
A11: 8 | B11: Dolo Pain Spray | C11: Pain Relief | D11: 195 | E11: 140 | F11: 38 | G11: 65 | H11: 48 | I11: 55 | J11: 9360 | K11: 04/2026
A12: 9 | B12: Abzolid 600 Tab | C12: Antibiotic | D12: 406 | E12: 285 | F12: 87 | G12: 38 | H12: 21 | I12: 104 | J12: 8526 | K12: 06/2026
A13: 10 | B13: Calbert D3 60K Cap | C13: Vitamin / Supplement | D13: 198 | E13: 135 | F13: 72 | G13: 59 | H13: 44 | I13: 87 | J13: 8712 | K13: 07/2026
A14: 11 | B14: Chymotas Forte Tab | C14: Pain / Swelling | D14: 370 | E14: 260 | F14: 42 | G14: 43 | H14: 33 | I14: 52 | J14: 12210 | K14: 05/2026
A15: 12 | B15: Skinshine Ointment 30g | C15: Dermatology | D15: 149 | E15: 105 | F15: 56 | G15: 69 | H15: 62 | I15: 63 | J15: 9238 | K15: 03/2026
... A33: 30 | B33: Moxib D Eye Drop | C33: Eye Care | D33: 110 | E33: 78 | F33: 85 | G33: 27 | H33: 27 | I33: 85 | J33: 2970 | K33: 06/2026

Sheet June 2026
A1: Anand Pharma, Darbhanga — Inventory & Sales Register (June 2026)
A3: S.No | B3: Medicine Name | C3: Category | D3: MRP (₹) | E3: Purchase Price (₹) | F3: Opening Stock | G3: Purchase Qty | H3: Sales Qty | I3: Closing Stock | J3: Total Sales Revenue (₹) | K3: Expiry Date
A4: 1 | B4: Rabitec DSR Cap | C4: Gastric Care | D4: 185 | E4: 130 | F4: 43 | G4: 50 | H4: 74 | I4: 19 | J4: 13690 | K4: 08/2026
A5: 2 | B5: Montas L Tab (10s) | C5: Respiratory / Cold | D5: 165 | E5: 115 | F5: 64 | G5: 31 | H5: 46 | I5: 49 | J5: 7590 | K5: 05/2026
A6: 3 | B6: Calbert K27 Cap | C6: Calcium / Supplement | D6: 247 | E6: 175 | F6: 48 | G6: 30 | H6: 23 | I6: 55 | J6: 5681 | K6: 03/2026
A7: 4 | B7: Ceroxim CV 500 Tab | C7: Antibiotic | D7: 480 | E7: 340 | F7: 79 | G7: 50 | H7: 64 | I7: 65 | J7: 30720 | K7: 11/2026
A8: 5 | B8: Pantobert D Tab | C8: Gastric Care | D8: 140 | E8: 95 | F8: 46 | G8: 42 | H8: 25 | I8: 63 | J8: 3500 | K8: 09/2026
A9: 6 | B9: Moxabert CV 625 Tab | C9: Antibiotic | D9: 225 | E9: 160 | F9: 57 | G9: 31 | H9: 26 | I9: 62 | J9: 5850 | K9: 10/2026
A10: 7 | B10: Chyawanprash 2KG | C10: Ayurvedic / Immunity | D10: 450 | E10: 330 | F10: 25 | G10: 40 | H10: 15 | I10: 50 | J10: 6750 | K10: 12/2026
A11: 8 | B11: Dolo Pain Spray | C11: Pain Relief | D11: 195 | E11: 140 | F11: 44 | G11: 37 | H11: 17 | I11: 64 | J11: 3315 | K11: 04/2026
A12: 9 | B12: Abzolid 600 Tab | C12: Antibiotic | D12: 406 | E12: 285 | F12: 45 | G12: 66 | H12: 40 | I12: 71 | J12: 16240 | K12: 06/2026
A13: 10 | B13: Calbert D3 60K Cap | C13: Vitamin / Supplement | D13: 198 | E13: 135 | F13: 56 | G13: 60 | H13: 41 | I13: 75 | J13: 8118 | K13: 07/2026
A14: 11 | B14: Chymotas Forte Tab | C14: Pain / Swelling | D14: 370 | E14: 260 | F14: 66 | G14: 29 | H14: 27 | I14: 68 | J14: 9990 | K14: 05/2026
A15: 12 | B15: Skinshine Ointment 30g | C15: Dermatology | D15: 149 | E15: 105 | F15: 67 | G15: 42 | H15: 72 | I15: 37 | J15: 10728 | K15: 03/2026
... A33: 30 | B33: Moxib D Eye Drop | C33: Eye Care | D33: 110 | E33: 78 | F33: 74 | G33: 43 | H33: 18 | I33: 99 | J33: 1980 | K33: 06/2026

Sheet ABC & FSN Analysis
A1: Anand Pharma, Darbhanga — Combined ABC & FSN Classification (Jan 2026 - June 2026 Total)
A3: S.No | B3: Medicine Name | C3: Category | D3: MRP (₹) | E3: Purchase Rate (₹) | F3: Total 6M Sales Qty | G3: Total 6M Revenue (₹) | H3: Cum. Revenue % | I3: ABC Category | J3: FSN Category | K3: Expiry Risk Level
A4: 1 | B4: Ceroxim CV 500 Tab | C4: Antibiotic | D4: 480 | E4: 340 | F4: 241 | G4: 115680 | H4: 8.86% | I4: Category A (High Value) | J4: Slow Moving (S) | K4: Low/Moderate
A5: 2 | B5: Chyawanprash 2KG | C5: Ayurvedic / Immunity | D5: 450 | E5: 330 | F5: 218 | G5: 98100 | H5: 16.37% | I5: Category A (High Value) | J5: Slow Moving (S) | K5: Low/Moderate
A6: 3 | B6: Abzolid 600 Tab | C6: Antibiotic | D6: 406 | E6: 285 | F6: 228 | G6: 92568 | H6: 23.46% | I6: Category A (High Value) | J6: Slow Moving (S) | K6: Low/Moderate
A7: 4 | B7: Chymotas Forte Tab | C7: Pain / Swelling | D7: 370 | E7: 260 | F7: 185 | G7: 68450 | H7: 28.71% | I7: Category A (High Value) | J7: Non Moving (N) | K7: Low/Moderate
A8: 5 | B8: Deca-Intabolin 50mg Inj | C8: Steroid / Inj | D8: 280 | E8: 195 | F8: 232 | G8: 64960 | H8: 33.68% | I8: Category A (High Value) | J8: Slow Moving (S) | K8: Low/Moderate
A9: 6 | B9: Calbert K27 Cap | C9: Calcium / Supplement | D9: 247 | E9: 175 | F9: 245 | G9: 60515 | H9: 38.32% | I9: Category A (High Value) | J9: Slow Moving (S) | K9: Low/Moderate
A10: 7 | B10: Rabitec DSR Cap | C10: Gastric Care | D10: 185 | E10: 130 | F10: 317 | G10: 58645 | H10: 42.81% | I10: Category A (High Value) | J10: Fast Moving (F) | K10: Low/Moderate
A11: 8 | B11: Itra-Albert 200mg Cap | C11: Antifungal | D11: 225 | E11: 160 | F11: 259 | G11: 58275 | H11: 47.27% | I11: Category A (High Value) | J11: Fast Moving (F) | K11: Low/Moderate
A12: 9 | B12: Montas FX Tab | C12: Respiratory / Allergy | D12: 210 | E12: 148 | F12: 236 | G12: 49560 | H12: 51.07% | I12: Category A (High Value) | J12: Slow Moving (S) | K12: Low/Moderate
A13: 10 | B13: Calbert D3 60K Cap | C13: Vitamin / Supplement | D13: 198 | E13: 135 | F13: 246 | G13: 48708 | H13: 54.80% | I13: Category A (High Value) | J13: Slow Moving (S) | K13: Low/Moderate
A14: 11 | B14: Montas L Tab (10s) | C14: Respiratory / Cold | D14: 165 | E14: 115 | F14: 288 | G14: 47520 | H14: 58.44% | I14: Category A (High Value) | J14: Fast Moving (F) | K14: Low/Moderate
A15: 12 | B15: Ketomac Shampoo 100ml | C15: Dermatology | D15: 220 | E15: 155 | F15: 216 | G15: 47520 | H15: 62.08% | I15: Category A (High Value) | J15: Slow Moving (S) | K15: Low/Moderate
... A33: 30 | B33: Gentalab 30ml Inj | C33: Injectable | D33: 45 | E33: 28 | F33: 169 | G33: 7605 | H33: 100.00% | I33: Category C (Low Value) | J33: Non Moving (N) | K33: Low/Moderate
A36: 3.2 Descriptive Statistics & Quantitative Summary (30 Medicine SKUs)
A37: Statistical Metric | B37: MRP (₹) | C37: Purchase Price (₹) | D37: 6M Sales Qty (Strips) | E37: 6M Total Revenue (₹)
A38: Sample Count (N) | B38: =COUNT(D4:D33) | C38: =COUNT(E4:E33) | D38: =COUNT(F4:F33) | E38: =COUNT(G4:G33)
A39: Mean (Average) | B39: =AVERAGE(D4:D33) | C39: =AVERAGE(E4:E33) | D39: =AVERAGE(F4:F33) | E39: =AVERAGE(G4:G33)
A40: Median | B40: =MEDIAN(D4:D33) | C40: =MEDIAN(E4:E33) | D40: =MEDIAN(F4:F33) | E40: =MEDIAN(G4:G33)
A41: Standard Deviation | B41: =STDEV(D4:D33) | C41: =STDEV(E4:E33) | D41: =STDEV(F4:F33) | E41: =STDEV(G4:G33)
A42: Minimum | B42: =MIN(D4:D33) | C42: =MIN(E4:E33) | D42: =MIN(F4:F33) | E42: =MIN(G4:G33)
A43: Maximum | B43: =MAX(D4:D33) | C43: =MAX(E4:E33) | D43: =MAX(F4:F33) | E43: =MAX(G4:G33)
A44: Range (Max - Min) | B44: =MAX(D4:D33)-MIN(D4:D33) | C44: =MAX(E4:E33)-MIN(E4:E33) | D44: =MAX(F4:F33)-MIN(F4:F33) | E44: =MAX(G4:G33)-MIN(G4:G33)

Sheet Monthly Sales Summary
A1: Month | B1: Total Revenue (₹) | C1: Total Units Sold
A2: Jan 2026 | B2: 220925 | C2: 1070
A3: Feb 2026 | B3: 214824 | C3: 1085
A4: Mar 2026 | B4: 207518 | C4: 1128
A5: Apr 2026 | B5: 197038 | C5: 991
A6: May 2026 | B6: 243998 | C6: 1265
A7: June 2026 | B7: 221352 | C7: 1163

Sheet Descriptive Statistics
A1: Anand Pharma, Darbhanga — Primary Dataset Descriptive Statistics
A2: Observation Period: January 2026 to June 2026 (N = 30 Medicine SKUs)
A4: Statistical Metric | B4: MRP (₹) | C4: Purchase Price (₹) | D4: 6M Sales Qty (Strips) | E4: 6M Total Revenue (₹)
A5: Sample Count (N) | B5: =COUNT('ABC & FSN Analysis'!D4:D33) | C5: =COUNT('ABC & FSN Analysis'!E4:E33) | D5: =COUNT('ABC & FSN Analysis'!F4:F33) | E5: =COUNT('ABC & FSN Analysis'!G4:G33)
A6: Mean (Average) | B6: =AVERAGE('ABC & FSN Analysis'!D4:D33) | C6: =AVERAGE('ABC & FSN Analysis'!E4:E33) | D6: =AVERAGE('ABC & FSN Analysis'!F4:F33) | E6: =AVERAGE('ABC & FSN Analysis'!G4:G33)
A7: Median | B7: =MEDIAN('ABC & FSN Analysis'!D4:D33) | C7: =MEDIAN('ABC & FSN Analysis'!E4:E33) | D7: =MEDIAN('ABC & FSN Analysis'!F4:F33) | E7: =MEDIAN('ABC & FSN Analysis'!G4:G33)
A8: Standard Deviation | B8: =STDEV('ABC & FSN Analysis'!D4:D33) | C8: =STDEV('ABC & FSN Analysis'!E4:E33) | D8: =STDEV('ABC & FSN Analysis'!F4:F33) | E8: =STDEV('ABC & FSN Analysis'!G4:G33)
A9: Minimum | B9: =MIN('ABC & FSN Analysis'!D4:D33) | C9: =MIN('ABC & FSN Analysis'!E4:E33) | D9: =MIN('ABC & FSN Analysis'!F4:F33) | E9: =MIN('ABC & FSN Analysis'!G4:G33)
A10: Maximum | B10: =MAX('ABC & FSN Analysis'!D4:D33) | C10: =MAX('ABC & FSN Analysis'!E4:E33) | D10: =MAX('ABC & FSN Analysis'!F4:F33) | E10: =MAX('ABC & FSN Analysis'!G4:G33)
A11: Range (Max - Min) | B11: =MAX('ABC & FSN Analysis'!D4:D33)-MIN('ABC & FSN Analysis'!D4:D33) | C11: =MAX('ABC & FSN Analysis'!E4:E33)-MIN('ABC & FSN Analysis'!E4:E33) | D11: =MAX('ABC & FSN Analysis'!F4:F33)-MIN('ABC & FSN Analysis'!F4:F33) | E11: =MAX('ABC & FSN Analysis'!G4:G33)-MIN('ABC & FSN Analysis'!G4:G33)
